aws_hotel_helpers/__init__.py
aws_hotel_helpers/core.py
aws_hotel_helpers/dynamodb.py
aws_hotel_helpers/exceptions.py
aws_hotel_helpers/s3.py
aws_hotel_helpers/sns.py
aws_hotel_helpers/sqs.py
aws_hotel_helpers-0.3.1.dist-info/LICENSE
aws_hotel_helpers-0.3.1.dist-info/METADATA
aws_hotel_helpers-0.3.1.dist-info/WHEEL
aws_hotel_helpers-0.3.1.dist-info/top_level.txt
aws_hotel_helpers-0.3.1.dist-info/RECORD
