Metadata-Version: 2.1
Name: aws-hotel-helpers
Version: 0.3.1
Summary: AWS helper utilities for hotel management systems
Home-page: https://github.com/yourusername/aws-hotel-helpers
Author: Your Name
Author-email: your.email@example.com
License: UNKNOWN
Platform: UNKNOWN
Classifier: Development Status :: 3 - Alpha
Classifier: Intended Audience :: Developers
Classifier: License :: OSI Approved :: MIT License
Classifier: Operating System :: OS Independent
Classifier: Programming Language :: Python :: 3
Classifier: Programming Language :: Python :: 3.7
Classifier: Programming Language :: Python :: 3.8
Classifier: Programming Language :: Python :: 3.9
Requires-Python: >=3.7
License-File: LICENSE
Requires-Dist: boto3==1.35.57
Requires-Dist: botocore==1.35.57
Requires-Dist: docutils<0.17,>=0.16
